gvit/__init__.py
gvit/cli.py
gvit/env_registry.py
gvit/error_handler.py
gvit/git.py
gvit/logger.py
gvit/backends/__init__.py
gvit/backends/common.py
gvit/backends/conda.py
gvit/backends/uv.py
gvit/backends/venv.py
gvit/backends/virtualenv.py
gvit/commands/__init__.py
gvit/commands/clone.py
gvit/commands/commit.py
gvit/commands/config.py
gvit/commands/envs.py
gvit/commands/init.py
gvit/commands/logs.py
gvit/commands/pull.py
gvit/commands/setup.py
gvit/commands/status.py
gvit/commands/tree.py
gvit/utils/__init__.py
gvit/utils/exceptions.py
gvit/utils/globals.py
gvit/utils/schemas.py
gvit/utils/utils.py
gvit/utils/validators.py
gvit-1.0.2.dist-info/METADATA
gvit-1.0.2.dist-info/WHEEL
gvit-1.0.2.dist-info/entry_points.txt
gvit-1.0.2.dist-info/licenses/LICENSE
gvit-1.0.2.dist-info/RECORD
