Metadata-Version: 2.4
Name: gvit
Version: 1.0.2
Summary: Automates virtual environment management for Git repositories
Project-URL: Homepage, https://github.com/jaimemartinagui/gvit
License-Expression: MIT
License-File: LICENSE
Classifier: Operating System :: OS Independent
Classifier: Programming Language :: Python :: 3
Requires-Python: >=3.10
Requires-Dist: click<9.0.0,>=8.0.0
Requires-Dist: pyperclip<2.0.0,>=1.9.0
Requires-Dist: questionary<3.0.0,>=2.0.0
Requires-Dist: rich<15.0.0,>=14.0.0
Requires-Dist: toml<1.0.0,>=0.10.0
Requires-Dist: typer<1.0.0,>=0.19.0
Provides-Extra: dev
Requires-Dist: pytest-cov>=4.0.0; extra == 'dev'
Requires-Dist: pytest-mock>=3.12.0; extra == 'dev'
Requires-Dist: pytest>=7.0.0; extra == 'dev'
Provides-Extra: test
Requires-Dist: pytest-cov>=4.0.0; extra == 'test'
Requires-Dist: pytest-mock>=3.12.0; extra == 'test'
Requires-Dist: pytest>=7.0.0; extra == 'test'
